llamachain/__init__.py
llamachain/__main__.py
llamachain/__version__.py
llamachain/app.py
llamachain/config.py
llamachain/log.py
llamachain/py.typed
llamachain/analytics/__init__.py
llamachain/analytics/dashboard.py
llamachain/api/__init__.py
llamachain/api/app.py
llamachain/api/main.py
llamachain/api/endpoints/__init__.py
llamachain/api/endpoints/ai.py
llamachain/api/endpoints/analysis.py
llamachain/api/endpoints/blockchain.py
llamachain/api/endpoints/dashboard.py
llamachain/api/endpoints/security.py
llamachain/api/routes/__init__.py
llamachain/api/routes/nlp.py
llamachain/api/schemas/__init__.py
llamachain/api/schemas/blockchain.py
llamachain/blockchain/__init__.py
llamachain/blockchain/base.py
llamachain/blockchain/registry.py
llamachain/blockchain/ethereum/__init__.py
llamachain/blockchain/ethereum/chain.py
llamachain/blockchain/solana/__init__.py
llamachain/blockchain/solana/chain.py
llamachain/cli/__init__.py
llamachain/cli/main.py
llamachain/core/__init__.py
llamachain/core/constants.py
llamachain/core/db.py
llamachain/core/exceptions.py
llamachain/db/__init__.py
llamachain/db/base.py
llamachain/db/models.py
llamachain/db/session.py
llamachain/ml/__init__.py
llamachain/nlp/__init__.py
llamachain/nlp/cli.py
llamachain/nlp/entity.py
llamachain/nlp/examples.py
llamachain/nlp/generation.py
llamachain/nlp/intent.py
llamachain/nlp/processor.py
llamachain/security/__init__.py
llamachain/security/audit/__init__.py
llamachain/security/audit/analyzer.py
llamachain/security/audit/rules.py
llamachain/security/zk/__init__.py
llamachain/security/zk/verifier.py
llamachain/utils/__init__.py
llamachain/utils/config.py
llamachain/utils/crypto.py
llamachain/utils/formatting.py
llamachain/utils/time.py
llamachain/utils/validation.py
llamachain/web/__init__.py
llamachain/worker/__init__.py
llamachain/worker/main.py
llamachain-0.1.0.data/data/stubs/py_ecc/__init__.pyi
llamachain-0.1.0.data/data/stubs/py_ecc/bn128.pyi
llamachain-0.1.0.data/data/stubs/spacy/__init__.pyi
llamachain-0.1.0.dist-info/licenses/LICENSE
llamachain-0.1.0.dist-info/METADATA
llamachain-0.1.0.dist-info/WHEEL
llamachain-0.1.0.dist-info/entry_points.txt
llamachain-0.1.0.dist-info/top_level.txt
llamachain-0.1.0.dist-info/RECORD
